wxminer/__init__.py
wxminer/__main__.py
wxminer/wechat.py
wxminer-0.1.1.dist-info/LICENSE
wxminer-0.1.1.dist-info/METADATA
wxminer-0.1.1.dist-info/WHEEL
wxminer-0.1.1.dist-info/RECORD
