Metadata-Version: 2.1
Name: wxminer
Version: 0.1.1
Summary: Deep into WeChat
Home-page: https://github.com/xleven/wxminer
License: MIT
Author: xleven
Author-email: xleven@outlook.com
Requires-Python: >=3.10,<4.0
Classifier: License :: OSI Approved :: MIT License
Classifier: Programming Language :: Python :: 3
Classifier: Programming Language :: Python :: 3.10
Classifier: Programming Language :: Python :: 3.11
Requires-Dist: ibackupy (>=0.1.2,<0.2.0)
Requires-Dist: lxml (>=4.9.2,<5.0.0)
Requires-Dist: pandas (>=1.5.3,<2.0.0)
